{"day1_ts":1701406800,"members":{"4277943":{"global_score":0,"last_star_ts":1732971635,"completion_day_level":{"1":{"2":{"star_index":4155348,"get_star_ts":1732786961},"1":{"star_index":4149859,"get_star_ts":1732715563}},"2":{"2":{"star_index":4167654,"get_star_ts":1732957203},"1":{"star_index":4163671,"get_star_ts":1732898912}},"3":{"1":{"get_star_ts":1732971635,"star_index":4168663}}},"name":"richzelle","id":4277943,"stars":5,"local_score":57},"4218614":{"local_score":0,"id":4218614,"stars":0,"name":"Jose Enrico Yalung","last_star_ts":0,"completion_day_level":{},"global_score":0},"4173167":{"last_star_ts":1730774401,"completion_day_level":{"1":{"2":{"star_index":4069375,"get_star_ts":1730774401},"1":{"get_star_ts":1730703468,"star_index":4066876}}},"global_score":0,"name":"Reinan Contawi","id":4173167,"stars":2,"local_score":27},"4173171":{"stars":0,"id":4173171,"local_score":0,"last_star_ts":0,"completion_day_level":{},"global_score":0,"name":"angelofiestada"},"4218623":{"completion_day_level":{"1":{"2":{"star_index":4162134,"get_star_ts":1732885152},"1":{"get_star_ts":1732880082,"star_index":4161701}},"2":{"1":{"get_star_ts":1732891195,"star_index":4162786},"2":{"get_star_ts":1732892695,"star_index":4162964}},"4":{"1":{"get_star_ts":1732983541,"star_index":4170032},"2":{"get_star_ts":1732985995,"star_index":4170374}},"3":{"2":{"star_index":4169496,"get_star_ts":1732979590},"1":{"get_star_ts":1732970961,"star_index":4168610}}},"last_star_ts":1732985995,"global_score":0,"name":"Dominic Albert Mamaril","id":4218623,"stars":8,"local_score":101},"4552514":{"name":"CA-Tiglao","global_score":0,"completion_day_level":{},"last_star_ts":0,"local_score":0,"stars":0,"id":4552514},"4173168":{"name":"Lawrence Dumlao","global_score":0,"completion_day_level":{},"last_star_ts":0,"local_score":0,"id":4173168,"stars":0},"3191440":{"local_score":110,"id":3191440,"stars":6,"name":"JSintos","global_score":0,"completion_day_level":{"4":{"2":{"star_index":1035928,"get_star_ts":1701742368},"1":{"star_index":801368,"get_star_ts":1701671951}},"1":{"2":{"star_index":27898,"get_star_ts":1701414919},"1":{"get_star_ts":1701410269,"star_index":14276}},"2":{"2":{"star_index":454731,"get_star_ts":1701542982},"1":{"get_star_ts":1701542197,"star_index":452209}}},"last_star_ts":1701742368},"3181607":{"name":"ns-franciscampos","completion_day_level":{"18":{"1":{"get_star_ts":1703058607,"star_index":3018555}},"3":{"1":{"get_star_ts":1701655855,"star_index":754334},"2":{"star_index":833721,"get_star_ts":1701680012}},"1":{"1":{"star_index":24137,"get_star_ts":1701413563},"2":{"star_index":35804,"get_star_ts":1701417410}},"15":{"1":{"get_star_ts":1702621721,"star_index":2599070},"2":{"get_star_ts":1702625190,"star_index":2604740}},"12":{"1":{"get_star_ts":1702364434,"star_index":2289776}},"5":{"2":{"star_index":1087620,"get_star_ts":1701766561},"1":{"star_index":1077448,"get_star_ts":1701762615}},"19":{"1":{"star_index":2951207,"get_star_ts":1702976179}},"11":{"1":{"get_star_ts":1702346997,"star_index":2270732},"2":{"star_index":2270834,"get_star_ts":1702347169}},"9":{"1":{"get_star_ts":1702283368,"star_index":2163040},"2":{"get_star_ts":1702284315,"star_index":2165028}},"21":{"1":{"get_star_ts":1703137735,"star_index":3077309}},"4":{"1":{"get_star_ts":1701670065,"star_index":794104},"2":{"star_index":812199,"get_star_ts":1701674849}},"16":{"2":{"star_index":3070473,"get_star_ts":1703128462},"1":{"get_star_ts":1703124280,"star_index":3068925}},"8":{"2":{"get_star_ts":1702277643,"star_index":2151521},"1":{"get_star_ts":1702261202,"star_index":2123888}},"6":{"2":{"get_star_ts":1701842815,"star_index":1275880},"1":{"get_star_ts":1701842429,"star_index":1274592}},"7":{"2":{"star_index":2161170,"get_star_ts":1702282487},"1":{"star_index":2158850,"get_star_ts":1702281336}},"14":{"1":{"star_index":2491445,"get_star_ts":1702532646}},"13":{"2":{"get_star_ts":1702524457,"star_index":2480399},"1":{"star_index":2480159,"get_star_ts":1702523955}},"2":{"1":{"get_star_ts":1701651847,"star_index":749300},"2":{"get_star_ts":1701652293,"star_index":749895}},"10":{"1":{"star_index":2378059,"get_star_ts":1702439429}}},"last_star_ts":1703137735,"global_score":0,"local_score":598,"id":3181607,"stars":32},"4275579":{"local_score":50,"id":4275579,"stars":4,"name":"John Rey Sergio","global_score":0,"last_star_ts":1732686802,"completion_day_level":{"1":{"2":{"star_index":4147945,"get_star_ts":1732683766},"1":{"star_index":4147808,"get_star_ts":1732680850}},"2":{"1":{"get_star_ts":1732685952,"star_index":4148020},"2":{"get_star_ts":1732686802,"star_index":4148054}}}},"4173173":{"name":"Gladys Tomaub","global_score":0,"last_star_ts":0,"completion_day_level":{},"local_score":0,"stars":0,"id":4173173},"4173175":{"name":"pxoramos","last_star_ts":1730704480,"completion_day_level":{"1":{"1":{"get_star_ts":1730704480,"star_index":4066895}}},"global_score":0,"local_score":13,"id":4173175,"stars":1},"4218703":{"completion_day_level":{"1":{"2":{"star_index":4067691,"get_star_ts":1730729507},"1":{"star_index":4067009,"get_star_ts":1730709179}}},"last_star_ts":1730729507,"global_score":0,"name":"Kevin Viray","stars":2,"id":4218703,"local_score":25},"4173172":{"id":4173172,"stars":2,"local_score":28,"global_score":0,"completion_day_level":{"1":{"1":{"get_star_ts":1730704752,"star_index":4066902},"2":{"get_star_ts":1730707392,"star_index":4066955}}},"last_star_ts":1730707392,"name":"ajbulaong"},"3158126":{"global_score":0,"last_star_ts":1703750832,"completion_day_level":{"1":{"1":{"star_index":0,"get_star_ts":1701407458},"2":{"star_index":10274,"get_star_ts":1701409229}},"8":{"2":{"star_index":1670427,"get_star_ts":1702016580},"1":{"get_star_ts":1702012989,"star_index":1656425}},"6":{"1":{"get_star_ts":1701873170,"star_index":1369107},"2":{"star_index":1370284,"get_star_ts":1701873575}},"4":{"2":{"star_index":1127399,"get_star_ts":1701782425},"1":{"star_index":1125129,"get_star_ts":1701781533}},"3":{"2":{"get_star_ts":1701780102,"star_index":1121510},"1":{"star_index":1119025,"get_star_ts":1701779067}},"11":{"1":{"get_star_ts":1703575150,"star_index":3320917},"2":{"get_star_ts":1703575844,"star_index":3321033}},"2":{"1":{"get_star_ts":1701773544,"star_index":1106144},"2":{"star_index":1107917,"get_star_ts":1701774242}},"9":{"1":{"get_star_ts":1702370921,"star_index":2298046},"2":{"star_index":2299396,"get_star_ts":1702371934}},"10":{"2":{"star_index":3162170,"get_star_ts":1703259834},"1":{"star_index":3004612,"get_star_ts":1703036165}},"7":{"1":{"star_index":1547856,"get_star_ts":1701955299},"2":{"get_star_ts":1701958006,"star_index":1554288}},"12":{"1":{"get_star_ts":1703647787,"star_index":3343480},"2":{"get_star_ts":1703750832,"star_index":3369037}},"5":{"1":{"star_index":1133493,"get_star_ts":1701784776},"2":{"star_index":1136873,"get_star_ts":1701786132}}},"name":"doilie","stars":24,"id":3158126,"local_score":436},"4218634":{"local_score":204,"id":4218634,"stars":13,"name":"John Israel Aquino","completion_day_level":{"7":{"1":{"get_star_ts":1733225440,"star_index":4815177}},"4":{"2":{"get_star_ts":1731251276,"star_index":4084305},"1":{"get_star_ts":1731148112,"star_index":4081009}},"3":{"2":{"star_index":4080853,"get_star_ts":1731139056},"1":{"get_star_ts":1731139008,"star_index":4080850}},"5":{"1":{"get_star_ts":1731337399,"star_index":4087287},"2":{"get_star_ts":1731343848,"star_index":4087606}},"2":{"2":{"star_index":4080513,"get_star_ts":1731114084},"1":{"get_star_ts":1731113297,"star_index":4080499}},"1":{"1":{"star_index":4078156,"get_star_ts":1731058143},"2":{"star_index":4079386,"get_star_ts":1731084477}},"6":{"2":{"get_star_ts":1732064492,"star_index":4115131},"1":{"star_index":4115095,"get_star_ts":1732063317}}},"last_star_ts":1733225440,"global_score":0},"4173169":{"name":"Kei Shirabe","global_score":0,"completion_day_level":{"1":{"1":{"star_index":4066847,"get_star_ts":1730700640}}},"last_star_ts":1730700640,"local_score":16,"stars":1,"id":4173169},"4294538":{"name":"Not Gio","global_score":0,"last_star_ts":1733107709,"completion_day_level":{"9":{"2":{"get_star_ts":1733107709,"star_index":4387339},"1":{"get_star_ts":1733106015,"star_index":4385429}},"2":{"1":{"star_index":4162433,"get_star_ts":1732888025},"2":{"star_index":4162549,"get_star_ts":1732889038}},"7":{"1":{"get_star_ts":1733101257,"star_index":4379963},"2":{"get_star_ts":1733103887,"star_index":4383018}},"5":{"1":{"star_index":4195902,"get_star_ts":1733033178},"2":{"get_star_ts":1733058622,"star_index":4264289}},"1":{"1":{"get_star_ts":1732873445,"star_index":4161111},"2":{"star_index":4162232,"get_star_ts":1732886018}},"6":{"2":{"get_star_ts":1733039633,"star_index":4208591},"1":{"star_index":4208470,"get_star_ts":1733039585}},"8":{"1":{"get_star_ts":1733062620,"star_index":4275677},"2":{"get_star_ts":1733094565,"star_index":4370140}},"4":{"2":{"star_index":4167590,"get_star_ts":1732956118},"1":{"get_star_ts":1732953108,"star_index":4167447}},"3":{"2":{"star_index":4169756,"get_star_ts":1732981536},"1":{"get_star_ts":1732981516,"star_index":4169753}}},"local_score":268,"id":4294538,"stars":18},"4218626":{"id":4218626,"stars":2,"local_score":30,"global_score":0,"last_star_ts":1730728921,"completion_day_level":{"1":{"1":{"star_index":4066866,"get_star_ts":1730702539},"2":{"star_index":4067655,"get_star_ts":1730728921}}},"name":"Gracelda Nuqui"}},"event":"2023","owner_id":3158126}